leanforge/lean_canvas/__init__.py
leanforge/lean_canvas/admin.py
leanforge/lean_canvas/apps.py
leanforge/lean_canvas/forms/__init__.py
leanforge/lean_canvas/forms/channel.py
leanforge/lean_canvas/migrations/0001_initial.py
leanforge/lean_canvas/migrations/__init__.py
leanforge/lean_canvas/models/__init__.py
leanforge/lean_canvas/models/channel.py
leanforge/lean_canvas/models/cost_structure.py
leanforge/lean_canvas/models/customer_segment.py
leanforge/lean_canvas/models/key_metric.py
leanforge/lean_canvas/models/lean_canvas.py
leanforge/lean_canvas/models/problem.py
leanforge/lean_canvas/models/revenue_stream.py
leanforge/lean_canvas/models/solution.py
leanforge/lean_canvas/models/unfair_advantage.py
leanforge/lean_canvas/models/unique_value_proposition.py
leanforge/lean_canvas/templates/base.html
leanforge/lean_canvas/templates/lean_canvas/lean_canvas_detail.html
leanforge/lean_canvas/templates/lean_canvas/lean_canvas_list.html
leanforge/lean_canvas/templates/partials/channel_create.html
leanforge/lean_canvas/templates/partials/channel_form.html
leanforge/lean_canvas/templates/partials/channel_list.html
leanforge/lean_canvas/tests.py
leanforge/lean_canvas/urls.py
leanforge/lean_canvas/views/__init__.py
leanforge/lean_canvas/views/channel.py
leanforge/lean_canvas/views/lean_canvas.py
leanforge/leanforge/__init__.py
leanforge/leanforge/asgi.py
leanforge/leanforge/settings.py
leanforge/leanforge/urls.py
leanforge/leanforge/wsgi.py
leanforge/manage.py
leanforge-0.1.0.dist-info/WHEEL
leanforge-0.1.0.dist-info/METADATA
leanforge-0.1.0.dist-info/RECORD
